document_ingestor/__init__.py
document_ingestor/embedding_process.py
document_ingestor/eu_data_parser.py
document_ingestor/genericParser.py
document_ingestor/pdf_parser.py
document_ingestor-0.1.1.dist-info/LICENSE.txt
document_ingestor-0.1.1.dist-info/METADATA
document_ingestor-0.1.1.dist-info/WHEEL
document_ingestor-0.1.1.dist-info/top_level.txt
document_ingestor-0.1.1.dist-info/RECORD
