Metadata-Version: 2.1
Name: document_ingestor
Version: 0.1.1
Summary: This package consumes one or more Spanish constitution PDFs and then processes them to generate embedding vectors. The vectors are generated with OpenAI service and PineCone is used to store and retrieve embedding vectors.
Author-email: Milan Anand Raj <manandraj20@iitk.ac.in>
License: Copyright (c) 2018 The Python Packaging Authority
Project-URL: Homepage, https://github.com/pypa/sampleproject
Project-URL: Issues, https://github.com/pypa/sampleproject/issues
Classifier: Programming Language :: Python :: 3
Classifier: License :: OSI Approved :: MIT License
Classifier: Operating System :: OS Independent
Requires-Python: >=3.8
License-File: LICENSE.txt
Requires-Dist: pymupdf <=1.23.11
Requires-Dist: openai
Requires-Dist: pinecone-client
Requires-Dist: numpy
Requires-Dist: tiktoken
